{
  "todos": {
    "Coordinator": {
      "1": {
        "id": "1",
        "content": "Update package.json and basic project configuration",
        "details": "Change project name from solclock-unified to solpulse-dashboard, update any references",
        "status": "completed",
        "priority": "high"
      },
      "2": {
        "id": "2",
        "content": "Update color scheme in Tailwind config",
        "details": "Replace teal colors with blue purple theme using #13C9E1 (cyan) and #8A2BE2 (purple)",
        "status": "completed",
        "priority": "high"
      },
      "3": {
        "id": "3",
        "content": "Update layout.tsx and metadata",
        "details": "Change title, description, and any branding from SolClock to SolPulse",
        "status": "completed",
        "priority": "high"
      },
      "4": {
        "id": "4",
        "content": "Create SolPulse Logo component",
        "details": "Create a React component that uses the new logo image with proper sizing",
        "status": "completed",
        "priority": "high"
      },
      "5": {
        "id": "5",
        "content": "Update main dashboard (page.tsx)",
        "details": "Replace all SolClock references with SolPulse, update header logo, update all text content",
        "status": "completed",
        "priority": "high"
      },
      "6": {
        "id": "6",
        "content": "Update all other pages and components",
        "details": "Update analytics, tokens, alerts pages and any other components that reference SolClock",
        "status": "completed",
        "priority": "medium"
      },
      "7": {
        "id": "7",
        "content": "Generate and update favicon files",
        "details": "Convert the favicon image to proper ICO/PNG formats for web use",
        "status": "completed",
        "priority": "medium"
      },
      "8": {
        "id": "8",
        "content": "Test and validate the rebrand",
        "details": "Ensure all references are updated, colors work correctly, and no broken links",
        "status": "completed",
        "priority": "medium"
      }
    }
  }
}